[
  {
    "MATRICULA": 211012094044,
    "NOME": "ALICYA NHAYARA SILVA ANDRADE",
    "CURSO": "ADMINISTRACAO",
    "CIDADE": "ITABAIANA",
    "TURMA": "A0",
    "NOTA": 621.9,
    "POSICAO": "24º",
    "ESTADO": "SE"
  },
  {
    "MATRICULA": 211029189431,
    "NOME": "ANA CLARA DE SOUZA CRUZ",
    "CURSO": "ADMINISTRACAO",
    "CIDADE": "ITABAIANA",
    "TURMA": "A0",
    "NOTA": 655.9,
    "POSICAO": "6º",
    "ESTADO": "SE"
  },
  {
    "MATRICULA": 211025238984,
    "NOME": "ANA MILENA BISPO OLIVEIRA SANTOS",
    "CURSO": "AMINISTRACAO",
    "CIDADE": "ITABAIANA",
    "TURMA": "A0",
    "NOTA": 640.53,
    "POSICAO": "15º",
    "ESTADO": "SE"
  },
  {
    "MATRICULA": 211031640470,
    "NOME": "AISSA RAFAELY MOURA REZENDE",
    "CURSO": "AGROINDUSTRIA",
    "CIDADE": "CAMPUS DO SERTAO",
    "TURMA": "A0",
    "NOTA": 541.61,
    "POSICAO": "11º",
    "ESTADO": "SE"
  },
  {
    "MATRICULA": 211019563496,
    "NOME": "ANA JULIA SANTOS RABELO",
    "CURSO": "AGROINDUSTRIA",
    "CIDADE": "CAMPUS DO SERTAO",
    "TURMA": "L2",
    "NOTA": 536.64,
    "POSICAO": "6º",
    "ESTADO": "BA"
  },
  {
    "MATRICULA": 211009389621,
    "NOME": "BEATRIZ SANTOS DE OLIVEIRA",
    "CURSO": "AGROINDUSTRIA",
    "CIDADE": "CAMPUS DO SERTAO",
    "TURMA": "A0",
    "NOTA": 535.1,
    "POSICAO": "14º",
    "ESTADO": "BA"
  },
  {
    "MATRICULA": 211004337526,
    "NOME": "ALICIA VIEIRA FERREIRA",
    "CURSO": "ARQUEOLOGIA",
    "CIDADE": "LARANJEIRAS",
    "TURMA": "L5",
    "NOTA": 659.86,
    "POSICAO": "1º",
    "ESTADO": "MG"
  },
  {
    "MATRICULA": 211004816792,
    "NOME": "ALYCE SANTOS MARQUES",
    "CURSO": "ARQUEOLOGIA",
    "CIDADE": "LARANJEIRAS",
    "TURMA": "L2",
    "NOTA": 546.17,
    "POSICAO": "3º",
    "ESTADO": "SE"
  },
  {
    "MATRICULA": 211013344349,
    "NOME": "ANDRE LUIS ALMEIDA DE SOUSA",
    "CURSO": "ARQUEOLOGIA",
    "CIDADE": "LARANJEIRAS",
    "TURMA": "A0",
    "NOTA": 595.09,
    "POSICAO": "22º",
    "ESTADO": "BA"
  },
  {
    "MATRICULA": 211018738404,
    "NOME": "ALANNA DE OLIVEIRA SOUZA SILVA",
    "CURSO": "ARQUITETURA E URBANISMO",
    "CIDADE": "LARANJEIRAS",
    "TURMA": "A0",
    "NOTA": 709.45,
    "POSICAO": "14º",
    "ESTADO": "BA"
  },
  {
    "MATRICULA": 211028360611,
    "NOME": "ALEXANDRE FERREIRA MARTINS",
    "CURSO": "ARQUITETURA E URBANISMO",
    "CIDADE": "LARANJEIRAS",
    "TURMA": "L2",
    "NOTA": 626.94,
    "POSICAO": "7º",
    "ESTADO": "SE"
  },
  {
    "MATRICULA": 211011107516,
    "NOME": "ANA EMILIA SANTOS LUZ FRANCA",
    "CURSO": "ARQUITETURA E URBANISMO",
    "CIDADE": "LARANJEIRAS",
    "TURMA": "A0",
    "NOTA": 707.88,
    "POSICAO": "15º",
    "ESTADO": "BA"
  },
  {
    "MATRICULA": 211012262625,
    "NOME": "ALEX MATHEUS COLETA SANTOS",
    "CURSO": "CIENCIA DA COMPUTACAO",
    "CIDADE": "SAO CRISTOVAO",
    "TURMA": "A0",
    "NOTA": 752.3,
    "POSICAO": "12º",
    "ESTADO": "SE"
  },
  {
    "MATRICULA": 211007935755,
    "NOME": "ALEXANDRE DANTAS DOS SANTOS",
    "CURSO": "CIENCIA DA COMPUTACAO",
    "CIDADE": "SAO CRISTOVAO",
    "TURMA": "L2",
    "NOTA": 631.66,
    "POSICAO": "15º",
    "ESTADO": "SE"
  },
  {
    "MATRICULA": 211001516460,
    "NOME": "ALLAN GOMES DE ANDRADE",
    "CURSO": "CIENCIA DA COMPUTACAO",
    "CIDADE": "SAO CRISTOVAO",
    "TURMA": "L2",
    "NOTA": 657.32,
    "POSICAO": "4º",
    "ESTADO": "SE"
  }
]
